package com.flurry.sdk;

import android.text.TextUtils;
import android.view.ViewGroup;
import com.flurry.android.FlurryAdSize;
import com.flurry.android.impl.ads.FlurryAdModule;
import com.flurry.android.impl.ads.avro.protocol.v10.AdFrame;
import com.flurry.android.impl.ads.avro.protocol.v10.AdResponse;
import com.flurry.android.impl.ads.avro.protocol.v10.AdUnit;
import com.flurry.android.impl.ads.avro.protocol.v10.Configuration;
import java.util.Collections;
import java.util.Iterator;
import java.util.List;

class t$a
{
  private final String b;
  private t.b c;
  private List<AdUnit> d;

  public t$a(t paramt, String paramString)
  {
    this.b = paramString;
    this.c = t.b.a;
    a();
  }

  private void a(t.b paramb)
  {
    if (paramb == null);
    try
    {
      paramb = t.b.a;
      eo.a(3, t.d(), "Setting state from " + this.c + " to " + paramb);
      this.c = paramb;
      return;
    }
    finally
    {
    }
  }

  private void a(List<AdUnit> paramList, int paramInt)
  {
    try
    {
      boolean bool = t.b.a.equals(this.c);
      if (!bool);
      while (true)
      {
        return;
        this.d = paramList;
        a(t.b.d);
        b();
      }
    }
    finally
    {
    }
  }

  private void b()
  {
    while (true)
    {
      try
      {
        boolean bool = t.b.d.equals(this.c);
        if (!bool)
          return;
        Iterator localIterator1 = this.d.iterator();
        if (localIterator1.hasNext())
        {
          AdUnit localAdUnit = (AdUnit)localIterator1.next();
          if (localAdUnit.d() == null)
            continue;
          Iterator localIterator2 = localAdUnit.d().iterator();
          if (localIterator2.hasNext())
          {
            AdFrame localAdFrame = (AdFrame)localIterator2.next();
            String str = localAdFrame.c().toString();
            if (cj.a(str) <= 0)
              continue;
            t.a(this.a).a(localAdFrame.g().toString(), ck.a(str));
            continue;
          }
          continue;
        }
      }
      finally
      {
      }
      t.a(this.a).a(this.b, this.d);
      a();
    }
  }

  // ERROR //
  private void b(ViewGroup paramViewGroup, FlurryAdSize paramFlurryAdSize, boolean paramBoolean, AdUnit paramAdUnit)
  {
    // Byte code:
    //   0: aload_0
    //   1: monitorenter
    //   2: getstatic 136	com/flurry/sdk/t$b:b	Lcom/flurry/sdk/t$b;
    //   5: aload_0
    //   6: getfield 28	com/flurry/sdk/t$a:c	Lcom/flurry/sdk/t$b;
    //   9: invokevirtual 77	com/flurry/sdk/t$b:equals	(Ljava/lang/Object;)Z
    //   12: istore 6
    //   14: iload 6
    //   16: ifne +6 -> 22
    //   19: aload_0
    //   20: monitorexit
    //   21: return
    //   22: invokestatic 142	com/flurry/sdk/fc:i	()I
    //   25: invokestatic 145	com/flurry/sdk/fc:c	(I)Landroid/util/Pair;
    //   28: astore 7
    //   30: aload 7
    //   32: getfield 151	android/util/Pair:first	Ljava/lang/Object;
    //   35: checkcast 153	java/lang/Integer
    //   38: invokevirtual 156	java/lang/Integer:intValue	()I
    //   41: istore 8
    //   43: aload 7
    //   45: getfield 159	android/util/Pair:second	Ljava/lang/Object;
    //   48: checkcast 153	java/lang/Integer
    //   51: invokevirtual 156	java/lang/Integer:intValue	()I
    //   54: istore 9
    //   56: invokestatic 163	com/flurry/sdk/fc:j	()Landroid/util/Pair;
    //   59: astore 10
    //   61: aload 10
    //   63: getfield 151	android/util/Pair:first	Ljava/lang/Object;
    //   66: checkcast 153	java/lang/Integer
    //   69: invokevirtual 156	java/lang/Integer:intValue	()I
    //   72: istore 11
    //   74: aload 10
    //   76: getfield 159	android/util/Pair:second	Ljava/lang/Object;
    //   79: checkcast 153	java/lang/Integer
    //   82: invokevirtual 156	java/lang/Integer:intValue	()I
    //   85: istore 12
    //   87: aload_2
    //   88: ifnull +699 -> 787
    //   91: aload_2
    //   92: getstatic 169	com/flurry/android/FlurryAdSize:BANNER_BOTTOM	Lcom/flurry/android/FlurryAdSize;
    //   95: invokevirtual 170	com/flurry/android/FlurryAdSize:equals	(Ljava/lang/Object;)Z
    //   98: ifne +13 -> 111
    //   101: aload_2
    //   102: getstatic 173	com/flurry/android/FlurryAdSize:BANNER_TOP	Lcom/flurry/android/FlurryAdSize;
    //   105: invokevirtual 170	com/flurry/android/FlurryAdSize:equals	(Ljava/lang/Object;)Z
    //   108: ifeq +679 -> 787
    //   111: aload_1
    //   112: ifnull +668 -> 780
    //   115: aload_1
    //   116: invokevirtual 178	android/view/ViewGroup:getHeight	()I
    //   119: ifle +661 -> 780
    //   122: aload_1
    //   123: invokevirtual 178	android/view/ViewGroup:getHeight	()I
    //   126: invokestatic 181	com/flurry/sdk/fc:a	(I)I
    //   129: istore 13
    //   131: aload_1
    //   132: ifnull +637 -> 769
    //   135: aload_1
    //   136: invokevirtual 184	android/view/ViewGroup:getWidth	()I
    //   139: ifle +630 -> 769
    //   142: aload_1
    //   143: invokevirtual 184	android/view/ViewGroup:getWidth	()I
    //   146: invokestatic 181	com/flurry/sdk/fc:a	(I)I
    //   149: istore 29
    //   151: iload 13
    //   153: istore 14
    //   155: iload 29
    //   157: istore 15
    //   159: aload_0
    //   160: getfield 17	com/flurry/sdk/t$a:a	Lcom/flurry/sdk/t;
    //   163: invokestatic 116	com/flurry/sdk/t:a	(Lcom/flurry/sdk/t;)Lcom/flurry/android/impl/ads/FlurryAdModule;
    //   166: invokevirtual 187	com/flurry/android/impl/ads/FlurryAdModule:E	()Ljava/util/List;
    //   169: astore 16
    //   171: aload_0
    //   172: getfield 17	com/flurry/sdk/t$a:a	Lcom/flurry/sdk/t;
    //   175: invokestatic 116	com/flurry/sdk/t:a	(Lcom/flurry/sdk/t;)Lcom/flurry/android/impl/ads/FlurryAdModule;
    //   178: invokevirtual 190	com/flurry/android/impl/ads/FlurryAdModule:F	()Ljava/util/List;
    //   181: astore 17
    //   183: new 192	java/util/ArrayList
    //   186: dup
    //   187: invokespecial 193	java/util/ArrayList:<init>	()V
    //   190: astore 18
    //   192: aload_0
    //   193: getfield 17	com/flurry/sdk/t$a:a	Lcom/flurry/sdk/t;
    //   196: invokestatic 116	com/flurry/sdk/t:a	(Lcom/flurry/sdk/t;)Lcom/flurry/android/impl/ads/FlurryAdModule;
    //   199: invokevirtual 196	com/flurry/android/impl/ads/FlurryAdModule:U	()Z
    //   202: ifeq +31 -> 233
    //   205: aload 18
    //   207: ldc 198
    //   209: invokeinterface 201 2 0
    //   214: pop
    //   215: aload 18
    //   217: aload_0
    //   218: getfield 17	com/flurry/sdk/t$a:a	Lcom/flurry/sdk/t;
    //   221: invokestatic 116	com/flurry/sdk/t:a	(Lcom/flurry/sdk/t;)Lcom/flurry/android/impl/ads/FlurryAdModule;
    //   224: invokevirtual 204	com/flurry/android/impl/ads/FlurryAdModule:V	()Ljava/lang/CharSequence;
    //   227: invokeinterface 201 2 0
    //   232: pop
    //   233: aload 4
    //   235: ifnull +525 -> 760
    //   238: aload 4
    //   240: invokevirtual 208	com/flurry/android/impl/ads/avro/protocol/v10/AdUnit:s	()Ljava/lang/Boolean;
    //   243: invokevirtual 213	java/lang/Boolean:booleanValue	()Z
    //   246: istore 19
    //   248: aload 4
    //   250: invokevirtual 217	com/flurry/android/impl/ads/avro/protocol/v10/AdUnit:t	()Ljava/util/Map;
    //   253: astore 20
    //   255: iload 19
    //   257: istore 21
    //   259: aload 20
    //   261: astore 22
    //   263: invokestatic 222	com/flurry/android/impl/ads/avro/protocol/v10/AdRequest:b	()Lcom/flurry/android/impl/ads/avro/protocol/v10/AdRequest$Builder;
    //   266: aload_0
    //   267: getfield 17	com/flurry/sdk/t$a:a	Lcom/flurry/sdk/t;
    //   270: invokestatic 116	com/flurry/sdk/t:a	(Lcom/flurry/sdk/t;)Lcom/flurry/android/impl/ads/FlurryAdModule;
    //   273: invokevirtual 224	com/flurry/android/impl/ads/FlurryAdModule:j	()Ljava/lang/String;
    //   276: invokevirtual 229	com/flurry/android/impl/ads/avro/protocol/v10/AdRequest$Builder:a	(Ljava/lang/CharSequence;)Lcom/flurry/android/impl/ads/avro/protocol/v10/AdRequest$Builder;
    //   279: ldc 231
    //   281: invokevirtual 233	com/flurry/android/impl/ads/avro/protocol/v10/AdRequest$Builder:c	(Ljava/lang/CharSequence;)Lcom/flurry/android/impl/ads/avro/protocol/v10/AdRequest$Builder;
    //   284: aload_0
    //   285: getfield 17	com/flurry/sdk/t$a:a	Lcom/flurry/sdk/t;
    //   288: invokestatic 116	com/flurry/sdk/t:a	(Lcom/flurry/sdk/t;)Lcom/flurry/android/impl/ads/FlurryAdModule;
    //   291: invokevirtual 236	com/flurry/android/impl/ads/FlurryAdModule:X	()Ljava/util/List;
    //   294: invokevirtual 239	com/flurry/android/impl/ads/avro/protocol/v10/AdRequest$Builder:b	(Ljava/util/List;)Lcom/flurry/android/impl/ads/avro/protocol/v10/AdRequest$Builder;
    //   297: aload 16
    //   299: invokevirtual 241	com/flurry/android/impl/ads/avro/protocol/v10/AdRequest$Builder:a	(Ljava/util/List;)Lcom/flurry/android/impl/ads/avro/protocol/v10/AdRequest$Builder;
    //   302: aload_0
    //   303: getfield 17	com/flurry/sdk/t$a:a	Lcom/flurry/sdk/t;
    //   306: invokestatic 116	com/flurry/sdk/t:a	(Lcom/flurry/sdk/t;)Lcom/flurry/android/impl/ads/FlurryAdModule;
    //   309: invokevirtual 245	com/flurry/android/impl/ads/FlurryAdModule:n	()Lcom/flurry/android/impl/ads/avro/protocol/v10/Location;
    //   312: invokevirtual 248	com/flurry/android/impl/ads/avro/protocol/v10/AdRequest$Builder:a	(Lcom/flurry/android/impl/ads/avro/protocol/v10/Location;)Lcom/flurry/android/impl/ads/avro/protocol/v10/AdRequest$Builder;
    //   315: aload_0
    //   316: getfield 17	com/flurry/sdk/t$a:a	Lcom/flurry/sdk/t;
    //   319: invokestatic 116	com/flurry/sdk/t:a	(Lcom/flurry/sdk/t;)Lcom/flurry/android/impl/ads/FlurryAdModule;
    //   322: invokevirtual 251	com/flurry/android/impl/ads/FlurryAdModule:Y	()Z
    //   325: invokevirtual 254	com/flurry/android/impl/ads/avro/protocol/v10/AdRequest$Builder:a	(Z)Lcom/flurry/android/impl/ads/avro/protocol/v10/AdRequest$Builder;
    //   328: invokestatic 259	com/flurry/android/FlurryAgent:getAgentVersion	()I
    //   331: invokestatic 262	java/lang/Integer:toString	(I)Ljava/lang/String;
    //   334: invokevirtual 264	com/flurry/android/impl/ads/avro/protocol/v10/AdRequest$Builder:b	(Ljava/lang/CharSequence;)Lcom/flurry/android/impl/ads/avro/protocol/v10/AdRequest$Builder;
    //   337: aload_0
    //   338: getfield 17	com/flurry/sdk/t$a:a	Lcom/flurry/sdk/t;
    //   341: invokestatic 116	com/flurry/sdk/t:a	(Lcom/flurry/sdk/t;)Lcom/flurry/android/impl/ads/FlurryAdModule;
    //   344: invokevirtual 268	com/flurry/android/impl/ads/FlurryAdModule:h	()J
    //   347: invokevirtual 271	com/flurry/android/impl/ads/avro/protocol/v10/AdRequest$Builder:a	(J)Lcom/flurry/android/impl/ads/avro/protocol/v10/AdRequest$Builder;
    //   350: invokestatic 276	com/flurry/android/impl/ads/avro/protocol/v10/AdViewContainer:b	()Lcom/flurry/android/impl/ads/avro/protocol/v10/AdViewContainer$Builder;
    //   353: iload 9
    //   355: invokevirtual 281	com/flurry/android/impl/ads/avro/protocol/v10/AdViewContainer$Builder:d	(I)Lcom/flurry/android/impl/ads/avro/protocol/v10/AdViewContainer$Builder;
    //   358: iload 8
    //   360: invokevirtual 283	com/flurry/android/impl/ads/avro/protocol/v10/AdViewContainer$Builder:c	(I)Lcom/flurry/android/impl/ads/avro/protocol/v10/AdViewContainer$Builder;
    //   363: iload 14
    //   365: invokevirtual 285	com/flurry/android/impl/ads/avro/protocol/v10/AdViewContainer$Builder:b	(I)Lcom/flurry/android/impl/ads/avro/protocol/v10/AdViewContainer$Builder;
    //   368: iload 15
    //   370: invokevirtual 287	com/flurry/android/impl/ads/avro/protocol/v10/AdViewContainer$Builder:a	(I)Lcom/flurry/android/impl/ads/avro/protocol/v10/AdViewContainer$Builder;
    //   373: invokestatic 290	com/flurry/sdk/fc:d	()F
    //   376: invokevirtual 293	com/flurry/android/impl/ads/avro/protocol/v10/AdViewContainer$Builder:a	(F)Lcom/flurry/android/impl/ads/avro/protocol/v10/AdViewContainer$Builder;
    //   379: invokestatic 298	com/flurry/sdk/cc:a	()Lcom/flurry/android/impl/ads/avro/protocol/v10/ScreenOrientationType;
    //   382: invokevirtual 301	com/flurry/android/impl/ads/avro/protocol/v10/AdViewContainer$Builder:a	(Lcom/flurry/android/impl/ads/avro/protocol/v10/ScreenOrientationType;)Lcom/flurry/android/impl/ads/avro/protocol/v10/AdViewContainer$Builder;
    //   385: invokevirtual 304	com/flurry/android/impl/ads/avro/protocol/v10/AdViewContainer$Builder:a	()Lcom/flurry/android/impl/ads/avro/protocol/v10/AdViewContainer;
    //   388: invokevirtual 307	com/flurry/android/impl/ads/avro/protocol/v10/AdRequest$Builder:a	(Lcom/flurry/android/impl/ads/avro/protocol/v10/AdViewContainer;)Lcom/flurry/android/impl/ads/avro/protocol/v10/AdRequest$Builder;
    //   391: aload_0
    //   392: getfield 17	com/flurry/sdk/t$a:a	Lcom/flurry/sdk/t;
    //   395: invokestatic 116	com/flurry/sdk/t:a	(Lcom/flurry/sdk/t;)Lcom/flurry/android/impl/ads/FlurryAdModule;
    //   398: invokevirtual 310	com/flurry/android/impl/ads/FlurryAdModule:l	()Ljava/lang/String;
    //   401: invokevirtual 312	com/flurry/android/impl/ads/avro/protocol/v10/AdRequest$Builder:d	(Ljava/lang/CharSequence;)Lcom/flurry/android/impl/ads/avro/protocol/v10/AdRequest$Builder;
    //   404: aload_0
    //   405: getfield 17	com/flurry/sdk/t$a:a	Lcom/flurry/sdk/t;
    //   408: invokestatic 116	com/flurry/sdk/t:a	(Lcom/flurry/sdk/t;)Lcom/flurry/android/impl/ads/FlurryAdModule;
    //   411: invokevirtual 315	com/flurry/android/impl/ads/FlurryAdModule:m	()Ljava/lang/String;
    //   414: invokevirtual 318	com/flurry/android/impl/ads/avro/protocol/v10/AdRequest$Builder:e	(Ljava/lang/CharSequence;)Lcom/flurry/android/impl/ads/avro/protocol/v10/AdRequest$Builder;
    //   417: aload_0
    //   418: getfield 17	com/flurry/sdk/t$a:a	Lcom/flurry/sdk/t;
    //   421: invokestatic 116	com/flurry/sdk/t:a	(Lcom/flurry/sdk/t;)Lcom/flurry/android/impl/ads/FlurryAdModule;
    //   424: invokevirtual 321	com/flurry/android/impl/ads/FlurryAdModule:Z	()Ljava/lang/String;
    //   427: invokevirtual 324	com/flurry/android/impl/ads/avro/protocol/v10/AdRequest$Builder:f	(Ljava/lang/CharSequence;)Lcom/flurry/android/impl/ads/avro/protocol/v10/AdRequest$Builder;
    //   430: aload_0
    //   431: getfield 17	com/flurry/sdk/t$a:a	Lcom/flurry/sdk/t;
    //   434: invokestatic 116	com/flurry/sdk/t:a	(Lcom/flurry/sdk/t;)Lcom/flurry/android/impl/ads/FlurryAdModule;
    //   437: invokevirtual 327	com/flurry/android/impl/ads/FlurryAdModule:aa	()Ljava/lang/String;
    //   440: invokevirtual 329	com/flurry/android/impl/ads/avro/protocol/v10/AdRequest$Builder:g	(Ljava/lang/CharSequence;)Lcom/flurry/android/impl/ads/avro/protocol/v10/AdRequest$Builder;
    //   443: iconst_0
    //   444: invokevirtual 331	com/flurry/android/impl/ads/avro/protocol/v10/AdRequest$Builder:b	(Z)Lcom/flurry/android/impl/ads/avro/protocol/v10/AdRequest$Builder;
    //   447: aload_0
    //   448: getfield 17	com/flurry/sdk/t$a:a	Lcom/flurry/sdk/t;
    //   451: invokestatic 116	com/flurry/sdk/t:a	(Lcom/flurry/sdk/t;)Lcom/flurry/android/impl/ads/FlurryAdModule;
    //   454: invokevirtual 335	com/flurry/android/impl/ads/FlurryAdModule:T	()Lcom/flurry/sdk/ev$a;
    //   457: invokevirtual 339	com/flurry/sdk/ev$a:a	()I
    //   460: invokevirtual 342	com/flurry/android/impl/ads/avro/protocol/v10/AdRequest$Builder:a	(I)Lcom/flurry/android/impl/ads/avro/protocol/v10/AdRequest$Builder;
    //   463: aload 17
    //   465: invokevirtual 344	com/flurry/android/impl/ads/avro/protocol/v10/AdRequest$Builder:c	(Ljava/util/List;)Lcom/flurry/android/impl/ads/avro/protocol/v10/AdRequest$Builder;
    //   468: invokestatic 349	com/flurry/sdk/dn:a	()Lcom/flurry/sdk/dn;
    //   471: invokevirtual 352	com/flurry/sdk/dn:k	()Z
    //   474: invokevirtual 354	com/flurry/android/impl/ads/avro/protocol/v10/AdRequest$Builder:c	(Z)Lcom/flurry/android/impl/ads/avro/protocol/v10/AdRequest$Builder;
    //   477: invokestatic 360	java/util/Locale:getDefault	()Ljava/util/Locale;
    //   480: invokevirtual 363	java/util/Locale:getLanguage	()Ljava/lang/String;
    //   483: invokevirtual 365	com/flurry/android/impl/ads/avro/protocol/v10/AdRequest$Builder:h	(Ljava/lang/CharSequence;)Lcom/flurry/android/impl/ads/avro/protocol/v10/AdRequest$Builder;
    //   486: aload_0
    //   487: getfield 17	com/flurry/sdk/t$a:a	Lcom/flurry/sdk/t;
    //   490: invokestatic 116	com/flurry/sdk/t:a	(Lcom/flurry/sdk/t;)Lcom/flurry/android/impl/ads/FlurryAdModule;
    //   493: invokevirtual 368	com/flurry/android/impl/ads/FlurryAdModule:ab	()Ljava/lang/String;
    //   496: invokevirtual 370	com/flurry/android/impl/ads/avro/protocol/v10/AdRequest$Builder:i	(Ljava/lang/CharSequence;)Lcom/flurry/android/impl/ads/avro/protocol/v10/AdRequest$Builder;
    //   499: iload 21
    //   501: invokevirtual 372	com/flurry/android/impl/ads/avro/protocol/v10/AdRequest$Builder:e	(Z)Lcom/flurry/android/impl/ads/avro/protocol/v10/AdRequest$Builder;
    //   504: astore 24
    //   506: aload_0
    //   507: getfield 17	com/flurry/sdk/t$a:a	Lcom/flurry/sdk/t;
    //   510: invokestatic 375	com/flurry/sdk/t:b	(Lcom/flurry/sdk/t;)Lcom/flurry/android/impl/ads/avro/protocol/v10/Configuration;
    //   513: ifnonnull +192 -> 705
    //   516: iconst_1
    //   517: istore 25
    //   519: aload 24
    //   521: iload 25
    //   523: invokevirtual 377	com/flurry/android/impl/ads/avro/protocol/v10/AdRequest$Builder:d	(Z)Lcom/flurry/android/impl/ads/avro/protocol/v10/AdRequest$Builder;
    //   526: aload 18
    //   528: invokevirtual 379	com/flurry/android/impl/ads/avro/protocol/v10/AdRequest$Builder:d	(Ljava/util/List;)Lcom/flurry/android/impl/ads/avro/protocol/v10/AdRequest$Builder;
    //   531: aload_0
    //   532: getfield 17	com/flurry/sdk/t$a:a	Lcom/flurry/sdk/t;
    //   535: invokestatic 116	com/flurry/sdk/t:a	(Lcom/flurry/sdk/t;)Lcom/flurry/android/impl/ads/FlurryAdModule;
    //   538: invokevirtual 381	com/flurry/android/impl/ads/FlurryAdModule:k	()Ljava/util/List;
    //   541: invokevirtual 383	com/flurry/android/impl/ads/avro/protocol/v10/AdRequest$Builder:e	(Ljava/util/List;)Lcom/flurry/android/impl/ads/avro/protocol/v10/AdRequest$Builder;
    //   544: invokevirtual 386	com/flurry/android/impl/ads/avro/protocol/v10/AdRequest$Builder:a	()Lcom/flurry/android/impl/ads/avro/protocol/v10/AdRequest;
    //   547: astore 26
    //   549: iload_3
    //   550: ifeq +161 -> 711
    //   553: aload 26
    //   555: iload_3
    //   556: invokestatic 390	java/lang/Boolean:valueOf	(Z)Ljava/lang/Boolean;
    //   559: invokevirtual 393	com/flurry/android/impl/ads/avro/protocol/v10/AdRequest:a	(Ljava/lang/Boolean;)V
    //   562: aload_2
    //   563: ifnull +21 -> 584
    //   566: aload 26
    //   568: invokestatic 398	com/flurry/android/impl/ads/avro/protocol/v10/TestAds:b	()Lcom/flurry/android/impl/ads/avro/protocol/v10/TestAds$Builder;
    //   571: aload_2
    //   572: invokevirtual 401	com/flurry/android/FlurryAdSize:getValue	()I
    //   575: invokevirtual 406	com/flurry/android/impl/ads/avro/protocol/v10/TestAds$Builder:a	(I)Lcom/flurry/android/impl/ads/avro/protocol/v10/TestAds$Builder;
    //   578: invokevirtual 409	com/flurry/android/impl/ads/avro/protocol/v10/TestAds$Builder:a	()Lcom/flurry/android/impl/ads/avro/protocol/v10/TestAds;
    //   581: invokevirtual 412	com/flurry/android/impl/ads/avro/protocol/v10/AdRequest:a	(Lcom/flurry/android/impl/ads/avro/protocol/v10/TestAds;)V
    //   584: aload_0
    //   585: getfield 17	com/flurry/sdk/t$a:a	Lcom/flurry/sdk/t;
    //   588: invokestatic 116	com/flurry/sdk/t:a	(Lcom/flurry/sdk/t;)Lcom/flurry/android/impl/ads/FlurryAdModule;
    //   591: invokevirtual 415	com/flurry/android/impl/ads/FlurryAdModule:r	()Z
    //   594: ifeq +18 -> 612
    //   597: aload 26
    //   599: aload_0
    //   600: getfield 17	com/flurry/sdk/t$a:a	Lcom/flurry/sdk/t;
    //   603: invokestatic 116	com/flurry/sdk/t:a	(Lcom/flurry/sdk/t;)Lcom/flurry/android/impl/ads/FlurryAdModule;
    //   606: invokevirtual 417	com/flurry/android/impl/ads/FlurryAdModule:s	()Ljava/util/Map;
    //   609: invokevirtual 420	com/flurry/android/impl/ads/avro/protocol/v10/AdRequest:a	(Ljava/util/Map;)V
    //   612: aload 22
    //   614: ifnull +10 -> 624
    //   617: aload 26
    //   619: aload 22
    //   621: invokevirtual 422	com/flurry/android/impl/ads/avro/protocol/v10/AdRequest:b	(Ljava/util/Map;)V
    //   624: aload_0
    //   625: getstatic 423	com/flurry/sdk/t$b:c	Lcom/flurry/sdk/t$b;
    //   628: invokespecial 42	com/flurry/sdk/t$a:a	(Lcom/flurry/sdk/t$b;)V
    //   631: iconst_3
    //   632: invokestatic 51	com/flurry/sdk/t:d	()Ljava/lang/String;
    //   635: new 53	java/lang/StringBuilder
    //   638: dup
    //   639: invokespecial 54	java/lang/StringBuilder:<init>	()V
    //   642: ldc_w 425
    //   645: invokevirtual 60	java/lang/StringBuilder:append	(Ljava/lang/String;)Ljava/lang/StringBuilder;
    //   648: aload 26
    //   650: invokevirtual 63	java/lang/StringBuilder:append	(Ljava/lang/Object;)Ljava/lang/StringBuilder;
    //   653: invokevirtual 68	java/lang/StringBuilder:toString	()Ljava/lang/String;
    //   656: invokestatic 73	com/flurry/sdk/eo:a	(ILjava/lang/String;Ljava/lang/String;)V
    //   659: aload_0
    //   660: getfield 17	com/flurry/sdk/t$a:a	Lcom/flurry/sdk/t;
    //   663: invokestatic 428	com/flurry/sdk/t:d	(Lcom/flurry/sdk/t;)Lcom/flurry/sdk/w;
    //   666: aload_0
    //   667: aload_0
    //   668: getfield 17	com/flurry/sdk/t$a:a	Lcom/flurry/sdk/t;
    //   671: invokestatic 116	com/flurry/sdk/t:a	(Lcom/flurry/sdk/t;)Lcom/flurry/android/impl/ads/FlurryAdModule;
    //   674: invokevirtual 431	com/flurry/android/impl/ads/FlurryAdModule:w	()Ljava/lang/String;
    //   677: aload 26
    //   679: ldc 219
    //   681: ldc_w 433
    //   684: new 435	com/flurry/sdk/t$a$2
    //   687: dup
    //   688: aload_0
    //   689: invokespecial 438	com/flurry/sdk/t$a$2:<init>	(Lcom/flurry/sdk/t$a;)V
    //   692: invokevirtual 443	com/flurry/sdk/w:a	(Ljava/lang/Object;Ljava/lang/String;Lcom/flurry/sdk/gw;Ljava/lang/Class;Ljava/lang/Class;Lcom/flurry/sdk/w$a;)V
    //   695: goto -676 -> 19
    //   698: astore 5
    //   700: aload_0
    //   701: monitorexit
    //   702: aload 5
    //   704: athrow
    //   705: iconst_0
    //   706: istore 25
    //   708: goto -189 -> 519
    //   711: aload 26
    //   713: aload_0
    //   714: getfield 22	com/flurry/sdk/t$a:b	Ljava/lang/String;
    //   717: invokevirtual 446	com/flurry/android/impl/ads/avro/protocol/v10/AdRequest:a	(Ljava/lang/CharSequence;)V
    //   720: goto -158 -> 562
    //   723: astore 23
    //   725: iconst_5
    //   726: invokestatic 51	com/flurry/sdk/t:d	()Ljava/lang/String;
    //   729: new 53	java/lang/StringBuilder
    //   732: dup
    //   733: invokespecial 54	java/lang/StringBuilder:<init>	()V
    //   736: ldc_w 448
    //   739: invokevirtual 60	java/lang/StringBuilder:append	(Ljava/lang/String;)Ljava/lang/StringBuilder;
    //   742: aload 23
    //   744: invokevirtual 63	java/lang/StringBuilder:append	(Ljava/lang/Object;)Ljava/lang/StringBuilder;
    //   747: invokevirtual 68	java/lang/StringBuilder:toString	()Ljava/lang/String;
    //   750: invokestatic 73	com/flurry/sdk/eo:a	(ILjava/lang/String;Ljava/lang/String;)V
    //   753: aload_0
    //   754: invokevirtual 30	com/flurry/sdk/t$a:a	()V
    //   757: goto -738 -> 19
    //   760: iconst_0
    //   761: istore 21
    //   763: aconst_null
    //   764: astore 22
    //   766: goto -503 -> 263
    //   769: iload 13
    //   771: istore 14
    //   773: iload 11
    //   775: istore 15
    //   777: goto -618 -> 159
    //   780: iload 12
    //   782: istore 13
    //   784: goto -653 -> 131
    //   787: iload 11
    //   789: istore 15
    //   791: iload 12
    //   793: istore 14
    //   795: goto -636 -> 159
    //
    // Exception table:
    //   from	to	target	type
    //   2	14	698	finally
    //   22	87	698	finally
    //   91	111	698	finally
    //   115	131	698	finally
    //   135	151	698	finally
    //   159	233	698	finally
    //   238	255	698	finally
    //   263	516	698	finally
    //   519	549	698	finally
    //   553	562	698	finally
    //   566	584	698	finally
    //   584	612	698	finally
    //   617	624	698	finally
    //   624	695	698	finally
    //   711	720	698	finally
    //   725	757	698	finally
    //   263	516	723	java/lang/Exception
    //   519	549	723	java/lang/Exception
    //   553	562	723	java/lang/Exception
    //   566	584	723	java/lang/Exception
    //   584	612	723	java/lang/Exception
    //   617	624	723	java/lang/Exception
    //   711	720	723	java/lang/Exception
  }

  public void a()
  {
    try
    {
      em.a().a(this);
      a(t.b.a);
      this.d = null;
      return;
    }
    finally
    {
      localObject = finally;
      throw localObject;
    }
  }

  public void a(final ViewGroup paramViewGroup, final FlurryAdSize paramFlurryAdSize, final boolean paramBoolean, final AdUnit paramAdUnit)
  {
    while (true)
    {
      try
      {
        if (!t.b.a.equals(this.c))
        {
          eo.a(3, t.d(), "requestAds: request pending");
          return;
        }
        if (!ev.a().c())
        {
          eo.a(5, t.d(), "There is no network connectivity (requestAds will fail)");
          continue;
        }
      }
      finally
      {
      }
      if (t.a(this.a).j() == null)
      {
        eo.a(5, t.d(), "There is no API key (requestAds will fail)");
      }
      else
      {
        t.a(this.a).W().d();
        a(t.b.b);
        do.a().c(new ff()
        {
          public void a()
          {
            t.a.a(t.a.this, paramViewGroup, paramFlurryAdSize, paramBoolean, paramAdUnit);
          }
        });
      }
    }
  }
}

/* Location:           /home/patcon/Downloads/com.enflick.android.TextNow-dex2jar.jar
 * Qualified Name:     com.flurry.sdk.t.a
 * JD-Core Version:    0.6.2
 */