package textnow.bp;

public final class c
{
  // ERROR //
  public static textnow.bn.d a(java.lang.String paramString)
  {
    // Byte code:
    //   0: aload_0
    //   1: ifnull +582 -> 583
    //   4: new 16	org/json/JSONObject
    //   7: dup
    //   8: aload_0
    //   9: invokespecial 19	org/json/JSONObject:<init>	(Ljava/lang/String;)V
    //   12: astore_1
    //   13: aload_1
    //   14: ldc 21
    //   16: invokevirtual 25	org/json/JSONObject:getJSONObject	(Ljava/lang/String;)Lorg/json/JSONObject;
    //   19: astore 5
    //   21: new 27	textnow/bn/b
    //   24: dup
    //   25: invokespecial 28	textnow/bn/b:<init>	()V
    //   28: astore 6
    //   30: aload 5
    //   32: ldc 30
    //   34: invokevirtual 34	org/json/JSONObject:getJSONArray	(Ljava/lang/String;)Lorg/json/JSONArray;
    //   37: astore 7
    //   39: aload 7
    //   41: invokevirtual 40	org/json/JSONArray:length	()I
    //   44: istore 8
    //   46: aconst_null
    //   47: astore 9
    //   49: iload 8
    //   51: ifle +354 -> 405
    //   54: new 42	java/util/ArrayList
    //   57: dup
    //   58: invokespecial 43	java/util/ArrayList:<init>	()V
    //   61: astore 9
    //   63: iconst_0
    //   64: istore 10
    //   66: iload 10
    //   68: aload 7
    //   70: invokevirtual 40	org/json/JSONArray:length	()I
    //   73: if_icmpge +332 -> 405
    //   76: aload 7
    //   78: iload 10
    //   80: invokevirtual 46	org/json/JSONArray:getJSONObject	(I)Lorg/json/JSONObject;
    //   83: ldc 48
    //   85: invokevirtual 52	org/json/JSONObject:getString	(Ljava/lang/String;)Ljava/lang/String;
    //   88: invokevirtual 58	java/lang/String:toString	()Ljava/lang/String;
    //   91: astore 17
    //   93: aload 7
    //   95: iload 10
    //   97: invokevirtual 46	org/json/JSONArray:getJSONObject	(I)Lorg/json/JSONObject;
    //   100: ldc 60
    //   102: invokevirtual 52	org/json/JSONObject:getString	(Ljava/lang/String;)Ljava/lang/String;
    //   105: invokevirtual 58	java/lang/String:toString	()Ljava/lang/String;
    //   108: astore 18
    //   110: aload 7
    //   112: iload 10
    //   114: invokevirtual 46	org/json/JSONArray:getJSONObject	(I)Lorg/json/JSONObject;
    //   117: ldc 62
    //   119: invokevirtual 52	org/json/JSONObject:getString	(Ljava/lang/String;)Ljava/lang/String;
    //   122: invokevirtual 58	java/lang/String:toString	()Ljava/lang/String;
    //   125: astore 19
    //   127: aload 7
    //   129: iload 10
    //   131: invokevirtual 46	org/json/JSONArray:getJSONObject	(I)Lorg/json/JSONObject;
    //   134: ldc 64
    //   136: invokevirtual 52	org/json/JSONObject:getString	(Ljava/lang/String;)Ljava/lang/String;
    //   139: invokevirtual 58	java/lang/String:toString	()Ljava/lang/String;
    //   142: astore 20
    //   144: aload 7
    //   146: iload 10
    //   148: invokevirtual 46	org/json/JSONArray:getJSONObject	(I)Lorg/json/JSONObject;
    //   151: ldc 66
    //   153: invokevirtual 52	org/json/JSONObject:getString	(Ljava/lang/String;)Ljava/lang/String;
    //   156: invokevirtual 58	java/lang/String:toString	()Ljava/lang/String;
    //   159: astore 21
    //   161: aload 7
    //   163: iload 10
    //   165: invokevirtual 46	org/json/JSONArray:getJSONObject	(I)Lorg/json/JSONObject;
    //   168: ldc 68
    //   170: invokevirtual 52	org/json/JSONObject:getString	(Ljava/lang/String;)Ljava/lang/String;
    //   173: invokevirtual 58	java/lang/String:toString	()Ljava/lang/String;
    //   176: astore 22
    //   178: aload 7
    //   180: iload 10
    //   182: invokevirtual 46	org/json/JSONArray:getJSONObject	(I)Lorg/json/JSONObject;
    //   185: ldc 70
    //   187: invokevirtual 74	org/json/JSONObject:getInt	(Ljava/lang/String;)I
    //   190: istore 23
    //   192: aload 7
    //   194: iload 10
    //   196: invokevirtual 46	org/json/JSONArray:getJSONObject	(I)Lorg/json/JSONObject;
    //   199: ldc 76
    //   201: invokevirtual 52	org/json/JSONObject:getString	(Ljava/lang/String;)Ljava/lang/String;
    //   204: invokevirtual 58	java/lang/String:toString	()Ljava/lang/String;
    //   207: astore 24
    //   209: aload 7
    //   211: iload 10
    //   213: invokevirtual 46	org/json/JSONArray:getJSONObject	(I)Lorg/json/JSONObject;
    //   216: ldc 78
    //   218: invokevirtual 74	org/json/JSONObject:getInt	(Ljava/lang/String;)I
    //   221: istore 25
    //   223: aload 7
    //   225: iload 10
    //   227: invokevirtual 46	org/json/JSONArray:getJSONObject	(I)Lorg/json/JSONObject;
    //   230: ldc 80
    //   232: invokevirtual 52	org/json/JSONObject:getString	(Ljava/lang/String;)Ljava/lang/String;
    //   235: invokevirtual 58	java/lang/String:toString	()Ljava/lang/String;
    //   238: astore 26
    //   240: aload 7
    //   242: iload 10
    //   244: invokevirtual 46	org/json/JSONArray:getJSONObject	(I)Lorg/json/JSONObject;
    //   247: ldc 82
    //   249: invokevirtual 52	org/json/JSONObject:getString	(Ljava/lang/String;)Ljava/lang/String;
    //   252: invokevirtual 58	java/lang/String:toString	()Ljava/lang/String;
    //   255: astore 27
    //   257: aload 7
    //   259: iload 10
    //   261: invokevirtual 46	org/json/JSONArray:getJSONObject	(I)Lorg/json/JSONObject;
    //   264: ldc 84
    //   266: invokevirtual 52	org/json/JSONObject:getString	(Ljava/lang/String;)Ljava/lang/String;
    //   269: invokevirtual 58	java/lang/String:toString	()Ljava/lang/String;
    //   272: astore 28
    //   274: aload 7
    //   276: iload 10
    //   278: invokevirtual 46	org/json/JSONArray:getJSONObject	(I)Lorg/json/JSONObject;
    //   281: ldc 86
    //   283: invokevirtual 52	org/json/JSONObject:getString	(Ljava/lang/String;)Ljava/lang/String;
    //   286: invokevirtual 58	java/lang/String:toString	()Ljava/lang/String;
    //   289: astore 29
    //   291: new 88	textnow/bn/c
    //   294: dup
    //   295: invokespecial 89	textnow/bn/c:<init>	()V
    //   298: astore 30
    //   300: aload 30
    //   302: aload 29
    //   304: invokevirtual 92	textnow/bn/c:k	(Ljava/lang/String;)V
    //   307: aload 30
    //   309: aload 27
    //   311: invokevirtual 95	textnow/bn/c:i	(Ljava/lang/String;)V
    //   314: aload 30
    //   316: aload 22
    //   318: invokevirtual 98	textnow/bn/c:f	(Ljava/lang/String;)V
    //   321: aload 30
    //   323: iload 23
    //   325: invokevirtual 101	textnow/bn/c:a	(I)V
    //   328: aload 30
    //   330: aload 20
    //   332: invokevirtual 104	textnow/bn/c:d	(Ljava/lang/String;)V
    //   335: aload 30
    //   337: aload 28
    //   339: invokevirtual 107	textnow/bn/c:j	(Ljava/lang/String;)V
    //   342: aload 30
    //   344: aload 19
    //   346: invokevirtual 110	textnow/bn/c:c	(Ljava/lang/String;)V
    //   349: aload 30
    //   351: aload 21
    //   353: invokevirtual 113	textnow/bn/c:e	(Ljava/lang/String;)V
    //   356: aload 30
    //   358: aload 17
    //   360: invokevirtual 115	textnow/bn/c:a	(Ljava/lang/String;)V
    //   363: aload 30
    //   365: aload 18
    //   367: invokevirtual 118	textnow/bn/c:b	(Ljava/lang/String;)V
    //   370: aload 30
    //   372: aload 24
    //   374: invokevirtual 121	textnow/bn/c:g	(Ljava/lang/String;)V
    //   377: aload 30
    //   379: aload 26
    //   381: invokevirtual 124	textnow/bn/c:h	(Ljava/lang/String;)V
    //   384: aload 30
    //   386: iload 25
    //   388: invokevirtual 126	textnow/bn/c:b	(I)V
    //   391: aload 9
    //   393: aload 30
    //   395: invokevirtual 130	java/util/ArrayList:add	(Ljava/lang/Object;)Z
    //   398: pop
    //   399: iinc 10 1
    //   402: goto -336 -> 66
    //   405: aload 6
    //   407: aload 9
    //   409: invokevirtual 133	textnow/bn/b:a	(Ljava/util/ArrayList;)V
    //   412: aload 6
    //   414: aload 5
    //   416: ldc 84
    //   418: invokevirtual 52	org/json/JSONObject:getString	(Ljava/lang/String;)Ljava/lang/String;
    //   421: invokevirtual 58	java/lang/String:toString	()Ljava/lang/String;
    //   424: invokevirtual 134	textnow/bn/b:a	(Ljava/lang/String;)V
    //   427: aload 6
    //   429: aload 5
    //   431: ldc 136
    //   433: invokevirtual 52	org/json/JSONObject:getString	(Ljava/lang/String;)Ljava/lang/String;
    //   436: invokevirtual 58	java/lang/String:toString	()Ljava/lang/String;
    //   439: invokevirtual 137	textnow/bn/b:b	(Ljava/lang/String;)V
    //   442: aload 6
    //   444: aload 5
    //   446: ldc 70
    //   448: invokevirtual 74	org/json/JSONObject:getInt	(Ljava/lang/String;)I
    //   451: invokevirtual 138	textnow/bn/b:a	(I)V
    //   454: aload 6
    //   456: aload 5
    //   458: ldc 68
    //   460: invokevirtual 52	org/json/JSONObject:getString	(Ljava/lang/String;)Ljava/lang/String;
    //   463: invokevirtual 58	java/lang/String:toString	()Ljava/lang/String;
    //   466: invokevirtual 139	textnow/bn/b:c	(Ljava/lang/String;)V
    //   469: new 141	textnow/bn/d
    //   472: dup
    //   473: invokespecial 142	textnow/bn/d:<init>	()V
    //   476: astore_3
    //   477: aload_3
    //   478: aload 6
    //   480: invokevirtual 145	textnow/bn/d:a	(Ltextnow/bn/b;)V
    //   483: aload_3
    //   484: aload_1
    //   485: ldc 147
    //   487: invokevirtual 52	org/json/JSONObject:getString	(Ljava/lang/String;)Ljava/lang/String;
    //   490: invokevirtual 58	java/lang/String:toString	()Ljava/lang/String;
    //   493: invokevirtual 148	textnow/bn/d:a	(Ljava/lang/String;)V
    //   496: aload_3
    //   497: aload_1
    //   498: ldc 76
    //   500: invokevirtual 52	org/json/JSONObject:getString	(Ljava/lang/String;)Ljava/lang/String;
    //   503: invokevirtual 58	java/lang/String:toString	()Ljava/lang/String;
    //   506: invokevirtual 149	textnow/bn/d:b	(Ljava/lang/String;)V
    //   509: aload_3
    //   510: areturn
    //   511: astore 11
    //   513: aload 11
    //   515: invokevirtual 152	org/json/JSONException:printStackTrace	()V
    //   518: goto -91 -> 427
    //   521: astore_2
    //   522: aconst_null
    //   523: astore_3
    //   524: aload_2
    //   525: astore 4
    //   527: aload 4
    //   529: invokevirtual 152	org/json/JSONException:printStackTrace	()V
    //   532: aload_3
    //   533: areturn
    //   534: astore 12
    //   536: aload 12
    //   538: invokevirtual 152	org/json/JSONException:printStackTrace	()V
    //   541: goto -99 -> 442
    //   544: astore 13
    //   546: aload 13
    //   548: invokevirtual 152	org/json/JSONException:printStackTrace	()V
    //   551: goto -97 -> 454
    //   554: astore 14
    //   556: aload 14
    //   558: invokevirtual 152	org/json/JSONException:printStackTrace	()V
    //   561: goto -92 -> 469
    //   564: astore 15
    //   566: aload 15
    //   568: invokevirtual 152	org/json/JSONException:printStackTrace	()V
    //   571: goto -75 -> 496
    //   574: astore 16
    //   576: aload 16
    //   578: invokevirtual 152	org/json/JSONException:printStackTrace	()V
    //   581: aload_3
    //   582: areturn
    //   583: aconst_null
    //   584: areturn
    //   585: astore 4
    //   587: goto -60 -> 527
    //
    // Exception table:
    //   from	to	target	type
    //   412	427	511	org/json/JSONException
    //   4	46	521	org/json/JSONException
    //   54	63	521	org/json/JSONException
    //   66	399	521	org/json/JSONException
    //   405	412	521	org/json/JSONException
    //   469	477	521	org/json/JSONException
    //   513	518	521	org/json/JSONException
    //   536	541	521	org/json/JSONException
    //   546	551	521	org/json/JSONException
    //   556	561	521	org/json/JSONException
    //   427	442	534	org/json/JSONException
    //   442	454	544	org/json/JSONException
    //   454	469	554	org/json/JSONException
    //   483	496	564	org/json/JSONException
    //   496	509	574	org/json/JSONException
    //   477	483	585	org/json/JSONException
    //   566	571	585	org/json/JSONException
    //   576	581	585	org/json/JSONException
  }

  public static c a()
  {
    return d.a;
  }
}

/* Location:           /home/patcon/Downloads/com.enflick.android.TextNow-2-dex2jar.jar
 * Qualified Name:     textnow.bp.c
 * JD-Core Version:    0.6.2
 */